laboralkutxa/api.py
laboralkutxa/cli.py
laboralkutxa/constants.py
laboral_kutxa-0.2.1.dist-info/LICENSE
laboral_kutxa-0.2.1.dist-info/METADATA
laboral_kutxa-0.2.1.dist-info/WHEEL
laboral_kutxa-0.2.1.dist-info/entry_points.txt
laboral_kutxa-0.2.1.dist-info/top_level.txt
laboral_kutxa-0.2.1.dist-info/RECORD
